aserehe/__init__.py
aserehe/_cli.py
aserehe/_commit.py
aserehe/_version.py
aserehe/py.typed
aserehe-0.2.2.dist-info/METADATA
aserehe-0.2.2.dist-info/WHEEL
aserehe-0.2.2.dist-info/entry_points.txt
aserehe-0.2.2.dist-info/licenses/LICENSE
aserehe-0.2.2.dist-info/RECORD
