Metadata-Version: 2.4
Name: aserehe
Version: 0.2.2
Summary: a semantic release helper CLI
Project-URL: repository, https://github.com/lukany/aserehe
Author-email: Jan Lukány <lukany.jan@gmail.com>
License: MIT License
License-File: LICENSE
Classifier: Development Status :: 3 - Alpha
Classifier: Environment :: Console
Classifier: Framework :: Pytest
Classifier: Intended Audience :: Developers
Classifier: License :: OSI Approved :: MIT License
Classifier: Programming Language :: Python :: 3.11
Classifier: Programming Language :: Python :: 3.12
Classifier: Topic :: Software Development :: Version Control :: Git
Classifier: Topic :: Utilities
Requires-Python: <4.0.0,>=3.11
Requires-Dist: gitpython<4.0.0,>=3.1.43
Requires-Dist: semantic-version<3.0.0,>=2.10.0
Requires-Dist: typer<1.0.0,>=0.15.1
Requires-Dist: typing-extensions<5.0.0,>=4.12.2
